entangled/__init__.py
entangled/logging.py
entangled/main.py
entangled/parsing.py
entangled/py.typed
entangled/status.py
entangled/text_location.py
entangled/utility.py
entangled/version.py
entangled/commands/__init__.py
entangled/commands/brei.py
entangled/commands/main.py
entangled/commands/new.py
entangled/commands/reset.py
entangled/commands/status.py
entangled/commands/stitch.py
entangled/commands/sync.py
entangled/commands/tangle.py
entangled/commands/watch.py
entangled/config/__init__.py
entangled/config/annotation_method.py
entangled/config/config_data.py
entangled/config/config_update.py
entangled/config/document_style.py
entangled/config/language.py
entangled/config/markers.py
entangled/config/namespace_default.py
entangled/config/templates.py
entangled/config/version.py
entangled/errors/__init__.py
entangled/errors/internal.py
entangled/errors/user.py
entangled/hooks/__init__.py
entangled/hooks/base.py
entangled/hooks/build.py
entangled/hooks/quarto_attributes.py
entangled/hooks/repl.py
entangled/hooks/shebang.py
entangled/hooks/spdx_license.py
entangled/hooks/task.py
entangled/interface/__init__.py
entangled/interface/context.py
entangled/interface/document.py
entangled/io/__init__.py
entangled/io/filedb.py
entangled/io/stat.py
entangled/io/transaction.py
entangled/io/virtual.py
entangled/iterators/__init__.py
entangled/iterators/lines.py
entangled/iterators/peekable.py
entangled/iterators/run_generator.py
entangled/model/__init__.py
entangled/model/code_block.py
entangled/model/content.py
entangled/model/properties.py
entangled/model/reference_id.py
entangled/model/reference_map.py
entangled/model/reference_name.py
entangled/model/tangle.py
entangled/readers/__init__.py
entangled/readers/code.py
entangled/readers/delimiters.py
entangled/readers/markdown.py
entangled/readers/types.py
entangled/readers/yaml_header.py
entangled_cli-2.4.2.dist-info/METADATA
entangled_cli-2.4.2.dist-info/WHEEL
entangled_cli-2.4.2.dist-info/entry_points.txt
entangled_cli-2.4.2.dist-info/licenses/LICENSE
entangled_cli-2.4.2.dist-info/RECORD
