Metadata-Version: 2.4
Name: entangled-cli
Version: 2.4.2
Summary: Literate Programming toolbox
Project-URL: Homepage, https://entangled.github.io/
Project-URL: Repository, https://github.com/entangled/entangled.py
Author-email: Johan Hidding <j.hidding@esciencecenter.nl>
License-Expression: Apache-2.0
License-File: LICENSE
Requires-Python: <4,>=3.13
Requires-Dist: brei<0.3,>=0.2.3
Requires-Dist: click>=8.3.0
Requires-Dist: copier<10,>=9
Requires-Dist: filelock<4,>=3.12.0
Requires-Dist: msgspec>=0.20.0
Requires-Dist: pyyaml<7,>=6.0.1
Requires-Dist: repl-session>=0.2.0
Requires-Dist: rich-argparse<2,>=1.4.0
Requires-Dist: rich-click>=1.9.4
Requires-Dist: rich<15,>=13
Requires-Dist: tomlkit<0.13,>=0.12.1
Requires-Dist: typeguard>=4.4.4
Requires-Dist: watchfiles>=1.1.1
